CHANGELOG.txt
LICENSE.txt
MANIFEST.in
README.txt
ez_setup.py
setup.cfg
setup.py
ErrorDocument.egg-info/PKG-INFO
ErrorDocument.egg-info/SOURCES.txt
ErrorDocument.egg-info/dependency_links.txt
ErrorDocument.egg-info/entry_points.txt
ErrorDocument.egg-info/not-zip-safe
ErrorDocument.egg-info/requires.txt
ErrorDocument.egg-info/top_level.txt
doc/Makefile
doc/index.txt
doc/source/api.rst
doc/source/conf.py
doc/source/index.rst
doc/source/manual.rst
errordocument/__init__.py
example/README.txt
test/README.txt
test/doc.py