Metadata-Version: 1.0
Name: ErrorDocument
Version: 0.2.2
Summary: Provide formatted HTML pages when responses other than 200 OK are returned from a web application.
Home-page: http://jimmyg.org/work/code/errordocument/index.html
Author: James Gardner
Author-email: UNKNOWN
License: GNU AGPLv3
Platform: UNKNOWN
Classifier: Development Status :: 3 - Alpha
Classifier: License :: OSI Approved :: GNU Affero General Public License v3
Classifier: Programming Language :: Python :: 2
Classifier: Topic :: Software Development :: Libraries :: Python Modules
Classifier: Topic :: Internet :: WWW/HTTP :: Dynamic Content
